pystokes/__init__.py
pystokes/forceFields.c
pystokes/forceFields.cpython-310-darwin.so
pystokes/forceFields.pxd
pystokes/forceFields.pyx
pystokes/interface.c
pystokes/interface.cpython-310-darwin.so
pystokes/interface.pxd
pystokes/interface.pyx
pystokes/periodic.c
pystokes/periodic.cpython-310-darwin.so
pystokes/periodic.pxd
pystokes/periodic.pyx
pystokes/twoWalls.c
pystokes/twoWalls.cpython-310-darwin.so
pystokes/twoWalls.pxd
pystokes/twoWalls.pyx
pystokes/unbounded.c
pystokes/unbounded.cpython-310-darwin.so
pystokes/unbounded.pxd
pystokes/unbounded.pyx
pystokes/utils.c
pystokes/utils.cpython-310-darwin.so
pystokes/utils.pxd
pystokes/utils.pyx
pystokes/wallBounded.c
pystokes/wallBounded.cpython-310-darwin.so
pystokes/wallBounded.pxd
pystokes/wallBounded.pyx
pystokes/phoretic/__init__.py
pystokes/phoretic/unbounded.c
pystokes/phoretic/unbounded.cpython-310-darwin.so
pystokes/phoretic/unbounded.pxd
pystokes/phoretic/unbounded.pyx
pystokes/phoretic/wallBounded.c
pystokes/phoretic/wallBounded.cpython-310-darwin.so
pystokes/phoretic/wallBounded.pxd
pystokes/phoretic/wallBounded.pyx
pystokes-2.3.2.dist-info/LICENSE
pystokes-2.3.2.dist-info/METADATA
pystokes-2.3.2.dist-info/WHEEL
pystokes-2.3.2.dist-info/top_level.txt
pystokes-2.3.2.dist-info/RECORD
