Metadata-Version: 2.1
Name: pystokes
Version: 2.3.2
Summary: Phoresis and Stokesian hydrodynamics in Python
Home-page: https://github.com/rajeshrinet/pystokes
Author: The PyStokes team
Author-email: PyStokes@googlegroups.com
License: MIT
Platform: tested on macOS
Platform: windows
Platform: and LINUX
Classifier: License :: OSI Approved :: MIT License
Classifier: Operating System :: OS Independent
Classifier: Programming Language :: Python
Classifier: Programming Language :: Python :: 2
Classifier: Programming Language :: Python :: 2.7
Classifier: Programming Language :: Python :: 3
Classifier: Programming Language :: Python :: 3.7
License-File: LICENSE
Requires-Dist: cython
Requires-Dist: numpy
Requires-Dist: scipy
Requires-Dist: matplotlib
